fleet/__init__.py
fleet/v1/__init__.py
fleet/v1/errors.py
fleet/v1/client.py
fleet/v1/tests/__init__.py
fleet/v1/tests/test_machine.py
fleet/v1/tests/test_errors.py
fleet/v1/tests/test_fleet_object.py
fleet/v1/tests/test_client.py
fleet/v1/tests/test_unit.py
fleet/v1/tests/test_http_unix_socket.py
fleet/v1/objects/__init__.py
fleet/v1/objects/fleet_object.py
fleet/v1/objects/machine.py
fleet/v1/objects/unit_state.py
fleet/v1/objects/unit.py
fleet/http/__init__.py
fleet/http/unix_socket.py
fleet-0.1.1.dist-info/top_level.txt
fleet-0.1.1.dist-info/dependency_links.txt
fleet-0.1.1.dist-info/METADATA
fleet-0.1.1.dist-info/DESCRIPTION.rst
fleet-0.1.1.dist-info/metadata.json
fleet-0.1.1.dist-info/WHEEL
fleet-0.1.1.dist-info/RECORD
