Metadata-Version: 2.0
Name: fleet
Version: 0.1.1
Summary: A python client for the fleet v1 API
Home-page: https://github.com/cnelson/python-fleet
Author: Chris Nelson
Author-email: cnelson@cnelson.org
License: Apache License (2.0)
Keywords: coreos fleet v1 api client
Platform: UNKNOWN
Classifier: Development Status :: 3 - Alpha
Classifier: Topic :: Software Development :: Libraries
Classifier: Topic :: System :: Distributed Computing
Classifier: Intended Audience :: Developers
Classifier: License :: OSI Approved :: Apache Software License
Classifier: Programming Language :: Python :: 2
Classifier: Programming Language :: Python :: 2.6
Classifier: Programming Language :: Python :: 2.7
Classifier: Programming Language :: Python :: 3
Classifier: Programming Language :: Python :: 3.3
Classifier: Programming Language :: Python :: 3.4
Requires-Dist: google-api-python-client (==1.3.2)
